src/server.py
src/static/favicon.ico
src/static/css/fa-all.min.css
src/static/css/main.css
src/static/images/og-image.webp
src/static/js/config.js
src/static/js/htmx.min.js
src/static/js/main.js
src/templates/index.html
src/templates/partials/get-request.html
src/templates/partials/post-request.html
openai_api_tester-0.1.5.dist-info/METADATA
openai_api_tester-0.1.5.dist-info/WHEEL
openai_api_tester-0.1.5.dist-info/entry_points.txt
openai_api_tester-0.1.5.dist-info/top_level.txt
openai_api_tester-0.1.5.dist-info/RECORD
