Metadata-Version: 2.2
Name: openai-api-tester
Version: 0.1.5
Summary: A tool designed to interact with APIs compatible with OpenAI's format.
Requires-Python: >=3.12
Requires-Dist: fastapi>=0.115
Requires-Dist: httpx>=0.28.1
Requires-Dist: jinja2>=3.1
Requires-Dist: pygments>=2.19
Requires-Dist: python-multipart>=0.0.20
Requires-Dist: uvicorn>=0.34
